PyomoTools/__init__.py
PyomoTools/base/GenerateExpressionString.py
PyomoTools/base/__init__.py
PyomoTools/base/Solvers/DefaultSolver.py
PyomoTools/base/Solvers/TimedIncumbentSolver.py
PyomoTools/base/Solvers/WrappedSolver.py
PyomoTools/base/Solvers/__init__.py
PyomoTools/base/Solvers/tests/__init__.py
PyomoTools/base/Solvers/tests/test_TimedIncumbentSolver.py
PyomoTools/environ/AssertPyomoModelsEqual.py
PyomoTools/environ/FindLeastInfeasibleSolution.py
PyomoTools/environ/InfeasibilityReport.py
PyomoTools/environ/Load2DIndexedSet.py
PyomoTools/environ/LoadIndexedSet.py
PyomoTools/environ/Polytope.py
PyomoTools/environ/__init__.py
PyomoTools/environ/Formulations/AndOperator.py
PyomoTools/environ/Formulations/ConditionalGeq.py
PyomoTools/environ/Formulations/ConditionalLeq.py
PyomoTools/environ/Formulations/ConstrainContiguousBinarySeries.py
PyomoTools/environ/Formulations/DoubleSidedBigM.py
PyomoTools/environ/Formulations/MaxOperator.py
PyomoTools/environ/Formulations/MinOperator.py
PyomoTools/environ/Formulations/OrOperator.py
PyomoTools/environ/Formulations/PWL.py
PyomoTools/environ/Formulations/RealBinaryIndicator.py
PyomoTools/environ/Formulations/__init__.py
PyomoTools/environ/Formulations/test/__init__.py
PyomoTools/environ/Formulations/test/test_AndOperator.py
PyomoTools/environ/Formulations/test/test_ConditionalGeq.py
PyomoTools/environ/Formulations/test/test_ConditionalLeq.py
PyomoTools/environ/Formulations/test/test_ConstrainContiguousBinarySeries.py
PyomoTools/environ/Formulations/test/test_DoubleSidedBigM.py
PyomoTools/environ/Formulations/test/test_MaxOperator.py
PyomoTools/environ/Formulations/test/test_OrOperator.py
PyomoTools/environ/Formulations/test/test_PWL.py
PyomoTools/environ/Formulations/test/test_RealBinaryIndicator.py
PyomoTools/environ/IO/LoadModelSolutionFromDF.py
PyomoTools/environ/IO/LoadModelSolutionFromExcel.py
PyomoTools/environ/IO/LoadVarSolutionFromDF.py
PyomoTools/environ/IO/ModelToDF.py
PyomoTools/environ/IO/ModelToExcel.py
pyomotools-0.3.1.dist-info/licenses/LICENSE
pyomotools-0.3.1.dist-info/METADATA
pyomotools-0.3.1.dist-info/WHEEL
pyomotools-0.3.1.dist-info/top_level.txt
pyomotools-0.3.1.dist-info/RECORD
