Metadata-Version: 2.4
Name: PyomoTools
Version: 0.3.1
Summary: A collection of tools to aid in formulating and working with Pyomo models.
Author-email: Nathan Barrett <nb5786@pricneton.edu>
License: MIT License
Project-URL: Homepage, https://github.com/NathanDavisBarrett/PyomoTools
Platform: UNKNOWN
Requires-Python: >=3.7
License-File: LICENSE
Requires-Dist: numpy>=1.21.0
Requires-Dist: pyomo>=6.0
Requires-Dist: scipy>=1.7.0
Requires-Dist: pandas>=2.3.0
Requires-Dist: pwlf>=2.5.1
Requires-Dist: matplotlib>=3.9.0
Requires-Dist: pytest>=8.4.0
Requires-Dist: PyQt5>=5.15.0
Requires-Dist: XlsxWriter>=3.2.3
Requires-Dist: openpyxl>=3.1.5
Requires-Dist: pyyaml>=6.0.2
Requires-Dist: gurobipy>=12.0.0
Dynamic: license-file
